__init__.py
document_reader.py
html_templates.py
machinery_diagnostics_server.py
report_generator.py
iflow_mcp_lgdimaggio_predictive_maintenance_mcp-0.3.2.dist-info/licenses/LICENSE
iflow_mcp_lgdimaggio_predictive_maintenance_mcp-0.3.2.dist-info/METADATA
iflow_mcp_lgdimaggio_predictive_maintenance_mcp-0.3.2.dist-info/WHEEL
iflow_mcp_lgdimaggio_predictive_maintenance_mcp-0.3.2.dist-info/entry_points.txt
iflow_mcp_lgdimaggio_predictive_maintenance_mcp-0.3.2.dist-info/top_level.txt
iflow_mcp_lgdimaggio_predictive_maintenance_mcp-0.3.2.dist-info/RECORD
