Metadata-Version: 2.4
Name: iflow-mcp_lgdimaggio_predictive-maintenance-mcp
Version: 0.3.2
Summary: Proof of Concept: AI-Powered Predictive Maintenance & Fault Diagnosis MCP Server - Industrial machinery condition monitoring, vibration analysis, bearing diagnostics, and ML-based anomaly detection through Model Context Protocol
Author-email: Luigi Di Maggio <luigi.dimaggio@polito.it>
License: MIT
Project-URL: Homepage, https://github.com/LGDiMaggio/predictive-maintenance-mcp
Project-URL: Repository, https://github.com/LGDiMaggio/predictive-maintenance-mcp
Project-URL: Documentation, https://github.com/LGDiMaggio/predictive-maintenance-mcp/blob/main/README.md
Project-URL: Issues, https://github.com/LGDiMaggio/predictive-maintenance-mcp/issues
Project-URL: Discussions, https://github.com/LGDiMaggio/predictive-maintenance-mcp/discussions
Keywords: signal-processing,iiot,predictive-analytics,anomaly-detection,asset-management,envelope-analysis,predictive-maintenance,condition-monitoring,machine-failure,bearing-fault-diagnosis,industrial-iot,fault-diagnosis,vibration-analysis,claude-ai,industry-4-0,model-context-protocol,mcp-server,fastmcp,iso10816,claude-agents
Classifier: Development Status :: 4 - Beta
Classifier: Intended Audience :: Science/Research
Classifier: Intended Audience :: Manufacturing
Classifier: License :: OSI Approved :: MIT License
Classifier: Programming Language :: Python :: 3
Classifier: Programming Language :: Python :: 3.11
Classifier: Programming Language :: Python :: 3.12
Classifier: Topic :: Scientific/Engineering
Classifier: Topic :: Software Development :: Libraries :: Python Modules
Requires-Python: >=3.11
License-File: LICENSE
Requires-Dist: mcp[cli]>=1.16.0
Requires-Dist: numpy>=2.3.3
Requires-Dist: pandas>=2.3.3
Requires-Dist: plotly>=5.24.0
Requires-Dist: pydantic>=2.12.0
Requires-Dist: scikit-learn>=1.7.2
Requires-Dist: scipy>=1.16.2
Provides-Extra: dev
Requires-Dist: pytest>=8.0.0; extra == "dev"
Requires-Dist: pytest-cov>=4.1.0; extra == "dev"
Requires-Dist: pytest-asyncio>=0.23.0; extra == "dev"
Requires-Dist: black>=24.0.0; extra == "dev"
Requires-Dist: flake8>=7.0.0; extra == "dev"
Requires-Dist: mypy>=1.8.0; extra == "dev"
Requires-Dist: types-requests>=2.31.0; extra == "dev"
Dynamic: license-file
